{
  "meta": {
    "generated_at_local": "2026-07-10 10:08:13 KST",
    "generated_at_utc": "2026-07-10T01:08:38.711798+00:00",
    "timezone": "Asia/Seoul",
    "repository": "PJS-creator/daily-invest-monitor",
    "ref_name": "main"
  },
  "summary": {
    "total_new_press": 2,
    "total_new_sec": 0,
    "alert_tickers": [
      "EQ",
      "QTTB",
      "CRNX"
    ],
    "overall_judgement": "행동 고려"
  },
  "dashboard": [
    {
      "ticker": "EQ",
      "close": 2.9600000381469727,
      "pct": -6.031747665655118,
      "pt": 7.125,
      "pt_upside": 140.70945635731857,
      "mktcap": "$187.2M",
      "ev": "$154.1M",
      "net_cash": "$33.1M (2025-09-30)",
      "runway": "15.2m",
      "next": "mid-2026: EQ504 Phase 1 SAD/MAD + PoM (Colon biopsy PD) start",
      "new_pr": 0,
      "new_sec": 0,
      "alert": "VOL 3.5x"
    },
    {
      "ticker": "GPCR",
      "close": 55.13999938964844,
      "pct": 0.455456372344476,
      "pt": 104.59375,
      "pt_upside": 89.68761544751783,
      "mktcap": "$3.92B",
      "ev": "$2.41B",
      "net_cash": "$1.51B (2025-09-30 (pro forma incl. Dec-2025 offering))",
      "runway": "-",
      "next": "2026 Q1: ACCESS II 44-week results (company guidance)",
      "new_pr": 0,
      "new_sec": 0,
      "alert": "-"
    },
    {
      "ticker": "IKT",
      "close": 2.0399999618530273,
      "pct": -1.4492740269210325,
      "pt": 5.875,
      "pt_upside": 187.9902014637031,
      "mktcap": "$269.3M",
      "ev": "$109.2M",
      "net_cash": "$160.1M (2025-09-30 + Nov-2025 offering (pro forma est.))",
      "runway": "71.0m",
      "next": "2026 H1: IMPROVE-PAH Phase 3 initiation / first patient dosed",
      "new_pr": 0,
      "new_sec": 0,
      "alert": "-"
    },
    {
      "ticker": "IMMX",
      "close": 11.09000015258789,
      "pct": 0.8181832053444582,
      "pt": 19.75429,
      "pt_upside": 78.12704894679617,
      "mktcap": "$789.5M",
      "ev": "$681.0M",
      "net_cash": "$108.5M (Sep-2025 + Dec-2025 offering (pro forma))",
      "runway": "76.0m",
      "next": "2026 H1~H2: NEXICART-2 enrollment maturity / data updates",
      "new_pr": 0,
      "new_sec": 0,
      "alert": "-"
    },
    {
      "ticker": "MGTX",
      "close": 13.9399995803833,
      "pct": -1.414432518270048,
      "pt": 28.375,
      "pt_upside": 103.55093869536391,
      "mktcap": "$1.29B",
      "ev": "$1.12B",
      "net_cash": "$170.9M (2025 Q3 (pro forma))",
      "runway": "21.4m",
      "next": "2026: AAV-AQP1 (AQUAx2) pivotal Phase 2 enrollment/progress updates",
      "new_pr": 0,
      "new_sec": 0,
      "alert": "-"
    },
    {
      "ticker": "PRAX",
      "close": 333.1199951171875,
      "pct": 0.03904167891684018,
      "pt": 619.1111,
      "pt_upside": 85.85227818048098,
      "mktcap": "$9.29B",
      "ev": "$7.74B",
      "net_cash": "$1.55B ((pro forma))",
      "runway": "31.0m",
      "next": "2026 Q2: Vormatrigine POWER1 (adjunctive FOS) topline",
      "new_pr": 0,
      "new_sec": 0,
      "alert": "-"
    },
    {
      "ticker": "QTTB",
      "close": 12.59000015258789,
      "pct": -10.582384795396893,
      "pt": 14.25,
      "pt_upside": 13.18506614212307,
      "mktcap": "$213.5M",
      "ev": "$173.3M",
      "net_cash": "$40.2M ((pro forma est.))",
      "runway": "13.2m",
      "next": "mid-2026: SIGNAL-AA Part B topline (W36, open-label)",
      "new_pr": 0,
      "new_sec": 0,
      "alert": "PRICE -10.6%"
    },
    {
      "ticker": "QURE",
      "close": 44.47999954223633,
      "pct": 2.276380376089304,
      "pt": 64.85074,
      "pt_upside": 45.79752847888516,
      "mktcap": "$3.06B",
      "ev": "$2.88B",
      "net_cash": "$177.0M (2025-09-30)",
      "runway": "15.9m",
      "next": "2026 H1: AMT-130 FDA Type A meeting outcome / minutes",
      "new_pr": 0,
      "new_sec": 0,
      "alert": "-"
    },
    {
      "ticker": "AVBP",
      "close": 33.66999816894531,
      "pct": 0.8083731459030297,
      "pt": 43.63636,
      "pt_upside": 29.600125848081916,
      "mktcap": "$1.57B",
      "ev": "$1.26B",
      "net_cash": "$305.4M (2025-09-30)",
      "runway": "21.2m",
      "next": "early-2026: FURVENT Phase 3 topline",
      "new_pr": 2,
      "new_sec": 0,
      "alert": "-"
    },
    {
      "ticker": "CGEM",
      "close": 18.3799991607666,
      "pct": -0.27130300369629934,
      "pt": 31.54545,
      "pt_upside": 71.62922437633172,
      "mktcap": "$1.13B",
      "ev": "$690.6M",
      "net_cash": "$439.0M ((net cash as of latest filings))",
      "runway": "-",
      "next": "2026 H1: CLN-978 initial safety + B-cell depletion data (RA/SLE)",
      "new_pr": 0,
      "new_sec": 0,
      "alert": "-"
    },
    {
      "ticker": "CMPS",
      "close": 13.600000381469727,
      "pct": -2.6136753822413983,
      "pt": 23.6,
      "pt_upside": 73.52940689733711,
      "mktcap": "$1.84B",
      "ev": "$1.58B",
      "net_cash": "$259.0M ((pro forma))",
      "runway": "19.5m",
      "next": "early Q3 2026: COMP005 Part B 26-week data + COMP006 durability / re-dosing",
      "new_pr": 0,
      "new_sec": 0,
      "alert": "-"
    },
    {
      "ticker": "CRNX",
      "close": 83.62000274658203,
      "pct": 0.15571312269599957,
      "pt": 82.5,
      "pt_upside": -1.3393957304405957,
      "mktcap": "$8.85B",
      "ev": "$7.50B",
      "net_cash": "$1.35B (2025-09-30)",
      "runway": "43.0m",
      "next": "2026: PALSONIFY quarterly sales / net product revenue updates",
      "new_pr": 0,
      "new_sec": 0,
      "alert": "VOL 3.1x; PT 83.73→82.50"
    }
  ],
  "companies": [
    {
      "ticker": "EQ",
      "name": "Equillium",
      "close": 2.9600000381469727,
      "pct": -6.031747665655118,
      "volume": 2607185.0,
      "volume_x": 3.522746926091069,
      "last_price_date": "2026-07-09",
      "market_cap": 187150608,
      "enterprise_value": 154050608.0,
      "net_cash_m": 33.1,
      "runway_months": 15.2,
      "alerts": [
        "VOL 3.5x"
      ],
      "new_pr_count": 0,
      "new_sec_count": 0,
      "new_press": [],
      "new_sec": [],
      "next_catalyst": "mid-2026: EQ504 Phase 1 SAD/MAD + PoM (Colon biopsy PD) start",
      "checklist": [],
      "price_target": {
        "mean": 7.125,
        "low": 4.0,
        "high": 12.0,
        "median": 6.5,
        "analyst_count": 8,
        "recommendation_key": "strong_buy",
        "recommendation_mean": 1.0,
        "upside_pct": 140.70945635731857
      },
      "anchors": {
        "as_of": "2025-09-30",
        "net_cash_m": 33.1,
        "burn_m_per_month": 2.2,
        "burn_m_per_quarter": null,
        "burn_m_per_year": null,
        "runway_months": 15.2,
        "buyout_per_share": {
          "bear": 0.52,
          "base": 1.56,
          "bull": 4.99
        }
      },
      "errors": {
        "price_error": null,
        "press_errors": [],
        "sec_error": null
      }
    },
    {
      "ticker": "GPCR",
      "name": "Structure Therapeutics",
      "close": 55.13999938964844,
      "pct": 0.455456372344476,
      "volume": 438890.0,
      "volume_x": 0.5207139484280938,
      "last_price_date": "2026-07-09",
      "market_cap": 3919048448,
      "enterprise_value": 2409048448.0,
      "net_cash_m": 1510.0,
      "runway_months": null,
      "alerts": [],
      "new_pr_count": 0,
      "new_sec_count": 0,
      "new_press": [],
      "new_sec": [],
      "next_catalyst": "2026 Q1: ACCESS II 44-week results (company guidance)",
      "checklist": [],
      "price_target": {
        "mean": 104.59375,
        "low": 69.5,
        "high": 145.0,
        "median": 101.0,
        "analyst_count": 16,
        "recommendation_key": "strong_buy",
        "recommendation_mean": 1.375,
        "upside_pct": 89.68761544751783
      },
      "anchors": {
        "as_of": "2025-09-30 (pro forma incl. Dec-2025 offering)",
        "net_cash_m": 1510.0,
        "burn_m_per_month": null,
        "burn_m_per_quarter": 53.0,
        "burn_m_per_year": null,
        "runway_months": null,
        "buyout_per_share": {
          "bear": 42.88,
          "base": 106.51,
          "bull": 336.75
        }
      },
      "errors": {
        "price_error": null,
        "press_errors": [],
        "sec_error": null
      }
    },
    {
      "ticker": "IKT",
      "name": "Inhibikase Therapeutics",
      "close": 2.0399999618530273,
      "pct": -1.4492740269210325,
      "volume": 621001.0,
      "volume_x": 0.7276386231365275,
      "last_price_date": "2026-07-09",
      "market_cap": 269346592,
      "enterprise_value": 109246592.0,
      "net_cash_m": 160.1,
      "runway_months": 71.0,
      "alerts": [],
      "new_pr_count": 0,
      "new_sec_count": 0,
      "new_press": [],
      "new_sec": [],
      "next_catalyst": "2026 H1: IMPROVE-PAH Phase 3 initiation / first patient dosed",
      "checklist": [],
      "price_target": {
        "mean": 5.875,
        "low": 3.0,
        "high": 8.0,
        "median": 5.5,
        "analyst_count": 8,
        "recommendation_key": "none",
        "recommendation_mean": null,
        "upside_pct": 187.9902014637031
      },
      "anchors": {
        "as_of": "2025-09-30 + Nov-2025 offering (pro forma est.)",
        "net_cash_m": 160.1,
        "burn_m_per_month": 2.3,
        "burn_m_per_quarter": null,
        "burn_m_per_year": null,
        "runway_months": 71.0,
        "buyout_per_share": {
          "bear": 1.7,
          "base": 4.32,
          "bull": 12.67
        }
      },
      "errors": {
        "price_error": null,
        "press_errors": [],
        "sec_error": null
      }
    },
    {
      "ticker": "IMMX",
      "name": "Immix Biopharma",
      "close": 11.09000015258789,
      "pct": 0.8181832053444582,
      "volume": 1446934.0,
      "volume_x": 0.967135284134849,
      "last_price_date": "2026-07-09",
      "market_cap": 789496576,
      "enterprise_value": 680996576.0,
      "net_cash_m": 108.5,
      "runway_months": 76.0,
      "alerts": [],
      "new_pr_count": 0,
      "new_sec_count": 0,
      "new_press": [],
      "new_sec": [],
      "next_catalyst": "2026 H1~H2: NEXICART-2 enrollment maturity / data updates",
      "checklist": [],
      "price_target": {
        "mean": 19.75429,
        "low": 14.5,
        "high": 27.0,
        "median": 20.0,
        "analyst_count": 7,
        "recommendation_key": "none",
        "recommendation_mean": null,
        "upside_pct": 78.12704894679617
      },
      "anchors": {
        "as_of": "Sep-2025 + Dec-2025 offering (pro forma)",
        "net_cash_m": 108.5,
        "burn_m_per_month": 1.4,
        "burn_m_per_quarter": null,
        "burn_m_per_year": null,
        "runway_months": 76.0,
        "buyout_per_share": {
          "bear": 8.82,
          "base": 32.69,
          "bull": 67.43
        }
      },
      "errors": {
        "price_error": null,
        "press_errors": [],
        "sec_error": null
      }
    },
    {
      "ticker": "MGTX",
      "name": "MeiraGTx",
      "close": 13.9399995803833,
      "pct": -1.414432518270048,
      "volume": 1140643.0,
      "volume_x": 1.1250242878123018,
      "last_price_date": "2026-07-09",
      "market_cap": 1290976640,
      "enterprise_value": 1120076640.0,
      "net_cash_m": 170.9,
      "runway_months": 21.4,
      "alerts": [],
      "new_pr_count": 0,
      "new_sec_count": 0,
      "new_press": [],
      "new_sec": [],
      "next_catalyst": "2026: AAV-AQP1 (AQUAx2) pivotal Phase 2 enrollment/progress updates",
      "checklist": [],
      "price_target": {
        "mean": 28.375,
        "low": 19.0,
        "high": 50.0,
        "median": 26.5,
        "analyst_count": 8,
        "recommendation_key": "strong_buy",
        "recommendation_mean": 1.25,
        "upside_pct": 103.55093869536391
      },
      "anchors": {
        "as_of": "2025 Q3 (pro forma)",
        "net_cash_m": 170.9,
        "burn_m_per_month": null,
        "burn_m_per_quarter": 34.5,
        "burn_m_per_year": null,
        "runway_months": 21.4,
        "buyout_per_share": {
          "bear": 6.4,
          "base": 23.31,
          "bull": 76.34
        }
      },
      "errors": {
        "price_error": null,
        "press_errors": [],
        "sec_error": null
      }
    },
    {
      "ticker": "PRAX",
      "name": "Praxis Precision Medicines",
      "close": 333.1199951171875,
      "pct": 0.03904167891684018,
      "volume": 243311.0,
      "volume_x": 0.47760575849120307,
      "last_price_date": "2026-07-09",
      "market_cap": 9286977536,
      "enterprise_value": 7736977536.0,
      "net_cash_m": 1550.0,
      "runway_months": 31.0,
      "alerts": [],
      "new_pr_count": 0,
      "new_sec_count": 0,
      "new_press": [],
      "new_sec": [],
      "next_catalyst": "2026 Q2: Vormatrigine POWER1 (adjunctive FOS) topline",
      "checklist": [
        "vormatrigine / elsunersen 등 주요 마일스톤 업데이트"
      ],
      "price_target": {
        "mean": 619.1111,
        "low": 162.0,
        "high": 1201.0,
        "median": 562.5,
        "analyst_count": 18,
        "recommendation_key": "strong_buy",
        "recommendation_mean": 1.5,
        "upside_pct": 85.85227818048098
      },
      "anchors": {
        "as_of": "(pro forma)",
        "net_cash_m": 1550.0,
        "burn_m_per_month": null,
        "burn_m_per_quarter": null,
        "burn_m_per_year": 600.0,
        "runway_months": 31.0,
        "buyout_per_share": {
          "bear": 162,
          "base": 471,
          "bull": 1485
        }
      },
      "errors": {
        "price_error": null,
        "press_errors": [],
        "sec_error": null
      }
    },
    {
      "ticker": "QTTB",
      "name": "Q32 Bio",
      "close": 12.59000015258789,
      "pct": -10.582384795396893,
      "volume": 263412.0,
      "volume_x": 0.34763214434655,
      "last_price_date": "2026-07-09",
      "market_cap": 213481280,
      "enterprise_value": 173281280.0,
      "net_cash_m": 40.2,
      "runway_months": 13.2,
      "alerts": [
        "PRICE -10.6%"
      ],
      "new_pr_count": 0,
      "new_sec_count": 0,
      "new_press": [],
      "new_sec": [],
      "next_catalyst": "mid-2026: SIGNAL-AA Part B topline (W36, open-label)",
      "checklist": [
        "SIGNAL-AA Phase 2 업데이트"
      ],
      "price_target": {
        "mean": 14.25,
        "low": 10.0,
        "high": 20.0,
        "median": 13.5,
        "analyst_count": 4,
        "recommendation_key": "none",
        "recommendation_mean": null,
        "upside_pct": 13.18506614212307
      },
      "anchors": {
        "as_of": "(pro forma est.)",
        "net_cash_m": 40.2,
        "burn_m_per_month": 3.0,
        "burn_m_per_quarter": null,
        "burn_m_per_year": null,
        "runway_months": 13.2,
        "buyout_per_share": {
          "bear": 4.26,
          "base": 11.96,
          "bull": 42.84
        }
      },
      "errors": {
        "price_error": null,
        "press_errors": [],
        "sec_error": null
      }
    },
    {
      "ticker": "QURE",
      "name": "uniQure",
      "close": 44.47999954223633,
      "pct": 2.276380376089304,
      "volume": 1148749.0,
      "volume_x": 0.5111887579759978,
      "last_price_date": "2026-07-09",
      "market_cap": 3058191104,
      "enterprise_value": 2881191104.0,
      "net_cash_m": 177.0,
      "runway_months": 15.9,
      "alerts": [],
      "new_pr_count": 0,
      "new_sec_count": 0,
      "new_press": [],
      "new_sec": [],
      "next_catalyst": "2026 H1: AMT-130 FDA Type A meeting outcome / minutes",
      "checklist": [
        "AMT-130 / AMT-191 / AMT-260 업데이트"
      ],
      "price_target": {
        "mean": 64.85074,
        "low": 36.034107,
        "high": 92.90145,
        "median": 64.822014,
        "analyst_count": 11,
        "recommendation_key": "strong_buy",
        "recommendation_mean": 1.46154,
        "upside_pct": 45.79752847888516
      },
      "anchors": {
        "as_of": "2025-09-30",
        "net_cash_m": 177.0,
        "burn_m_per_month": 11.2,
        "burn_m_per_quarter": null,
        "burn_m_per_year": null,
        "runway_months": 15.9,
        "buyout_per_share": {
          "bear": 8.2,
          "base": 36.2,
          "bull": 122.0
        }
      },
      "errors": {
        "price_error": null,
        "press_errors": [],
        "sec_error": null
      }
    },
    {
      "ticker": "AVBP",
      "name": "ArriVent BioPharma",
      "close": 33.66999816894531,
      "pct": 0.8083731459030297,
      "volume": 373795.0,
      "volume_x": 0.6819048348757577,
      "last_price_date": "2026-07-09",
      "market_cap": 1568177792,
      "enterprise_value": 1262777792.0,
      "net_cash_m": 305.4,
      "runway_months": 21.2,
      "alerts": [],
      "new_pr_count": 2,
      "new_sec_count": 0,
      "new_press": [
        {
          "title": "American Mariners Protest Chinese Vessel Operating Under Jones Act Waiver in Louisiana",
          "url": "https://www.globenewswire.com/news-release/2026/07/09/3325260/0/en/american-mariners-protest-chinese-vessel-operating-under-jones-act-waiver-in-louisiana.html",
          "date_text": null,
          "source": "GlobeNewswire"
        },
        {
          "title": "REVERSIBLE Addresses Online Fashion Inventory Fragmentation With Retail and Marketplace Aggregation",
          "url": "https://www.globenewswire.com/news-release/2026/07/09/3325242/0/en/reversible-addresses-online-fashion-inventory-fragmentation-with-retail-and-marketplace-aggregation.html",
          "date_text": null,
          "source": "GlobeNewswire"
        }
      ],
      "new_sec": [],
      "next_catalyst": "early-2026: FURVENT Phase 3 topline",
      "checklist": [
        "FURVENT / ALPACCA 관련 업데이트"
      ],
      "price_target": {
        "mean": 43.63636,
        "low": 34.0,
        "high": 50.0,
        "median": 45.0,
        "analyst_count": 11,
        "recommendation_key": "strong_buy",
        "recommendation_mean": 1.0,
        "upside_pct": 29.600125848081916
      },
      "anchors": {
        "as_of": "2025-09-30",
        "net_cash_m": 305.4,
        "burn_m_per_month": 14.4,
        "burn_m_per_quarter": null,
        "burn_m_per_year": null,
        "runway_months": 21.2,
        "buyout_per_share": {
          "bear": 20.57,
          "base": 56.74,
          "bull": 130.82
        }
      },
      "errors": {
        "price_error": null,
        "press_errors": [],
        "sec_error": null
      }
    },
    {
      "ticker": "CGEM",
      "name": "Cullinan Therapeutics",
      "close": 18.3799991607666,
      "pct": -0.27130300369629934,
      "volume": 441121.0,
      "volume_x": 0.4043961665325161,
      "last_price_date": "2026-07-09",
      "market_cap": 1129598848,
      "enterprise_value": 690598848.0,
      "net_cash_m": 439.0,
      "runway_months": null,
      "alerts": [],
      "new_pr_count": 0,
      "new_sec_count": 0,
      "new_press": [],
      "new_sec": [],
      "next_catalyst": "2026 H1: CLN-978 initial safety + B-cell depletion data (RA/SLE)",
      "checklist": [
        "CLN-978 / CLN-049 업데이트"
      ],
      "price_target": {
        "mean": 31.54545,
        "low": 24.0,
        "high": 38.0,
        "median": 30.0,
        "analyst_count": 11,
        "recommendation_key": "none",
        "recommendation_mean": null,
        "upside_pct": 71.62922437633172
      },
      "anchors": {
        "as_of": "(net cash as of latest filings)",
        "net_cash_m": 439.0,
        "burn_m_per_month": null,
        "burn_m_per_quarter": 36.5,
        "burn_m_per_year": null,
        "runway_months": null,
        "buyout_per_share": {
          "bear": 8.6,
          "base": 17.9,
          "bull": 45.9
        }
      },
      "errors": {
        "price_error": null,
        "press_errors": [],
        "sec_error": null
      }
    },
    {
      "ticker": "CMPS",
      "name": "Compass Pathways",
      "close": 13.600000381469727,
      "pct": -2.6136753822413983,
      "volume": 3018918.0,
      "volume_x": 0.6292439425548665,
      "last_price_date": "2026-07-09",
      "market_cap": 1835310720,
      "enterprise_value": 1576310720.0,
      "net_cash_m": 259.0,
      "runway_months": 19.5,
      "alerts": [],
      "new_pr_count": 0,
      "new_sec_count": 0,
      "new_press": [],
      "new_sec": [],
      "next_catalyst": "early Q3 2026: COMP005 Part B 26-week data + COMP006 durability / re-dosing",
      "checklist": [
        "Phase 3 관련 데이터/일정 업데이트"
      ],
      "price_target": {
        "mean": 23.6,
        "low": 8.0,
        "high": 70.0,
        "median": 20.0,
        "analyst_count": 15,
        "recommendation_key": "strong_buy",
        "recommendation_mean": 1.33333,
        "upside_pct": 73.52940689733711
      },
      "anchors": {
        "as_of": "(pro forma)",
        "net_cash_m": 259.0,
        "burn_m_per_month": 13.3,
        "burn_m_per_quarter": null,
        "burn_m_per_year": null,
        "runway_months": 19.5,
        "buyout_per_share": {
          "bear": 4.51,
          "base": 16.12,
          "bull": 60.45
        }
      },
      "errors": {
        "price_error": null,
        "press_errors": [],
        "sec_error": null
      }
    },
    {
      "ticker": "CRNX",
      "name": "Crinetics Pharmaceuticals",
      "close": 83.62000274658203,
      "pct": 0.15571312269599957,
      "volume": 9031979.0,
      "volume_x": 3.136683234541936,
      "last_price_date": "2026-07-09",
      "market_cap": 8850360320,
      "enterprise_value": 7500360320.0,
      "net_cash_m": 1350.0,
      "runway_months": 43.0,
      "alerts": [
        "VOL 3.1x",
        "PT 83.73→82.50"
      ],
      "new_pr_count": 0,
      "new_sec_count": 0,
      "new_press": [],
      "new_sec": [],
      "next_catalyst": "2026: PALSONIFY quarterly sales / net product revenue updates",
      "checklist": [
        "분기 실적/처방 지표 및 주요 임상 업데이트"
      ],
      "price_target": {
        "mean": 82.5,
        "low": 55.0,
        "high": 90.0,
        "median": 85.0,
        "analyst_count": 10,
        "recommendation_key": "hold",
        "recommendation_mean": 2.71429,
        "upside_pct": -1.3393957304405957
      },
      "anchors": {
        "as_of": "2025-09-30",
        "net_cash_m": 1350.0,
        "burn_m_per_month": 31.7,
        "burn_m_per_quarter": null,
        "burn_m_per_year": null,
        "runway_months": 43.0,
        "buyout_per_share": {
          "bear": 40.6,
          "base": 78.5,
          "bull": 139.2
        }
      },
      "errors": {
        "price_error": null,
        "press_errors": [],
        "sec_error": null
      }
    }
  ]
}